eqsolve/LICENSE.txt
eqsolve/README.md
eqsolve/__init__.py
eqsolve/equation/__init__.py
eqsolve/equation/contcompound.py
eqsolve/equation/findright.py
eqsolve/equation/intcompound.py
eqsolve/equation/issim.py
eqsolve/equation/midpoint.py
eqsolve/equation/perpint.py
eqsolve/equation/quadsolve.py
eqsolve/equation/slopeint.py
eqsolve/other/__init__.py
eqsolve/other/commands.py
eqsolve/other/help.py
eqsolve-1.0.1.dist-info/METADATA
eqsolve-1.0.1.dist-info/WHEEL
eqsolve-1.0.1.dist-info/top_level.txt
eqsolve-1.0.1.dist-info/RECORD
